[
  {
    "team": {
      "id": 1359,
      "name": "Luton",
      "logo": "https://media.api-sports.io/football/teams/1359.png",
      "colors": {
        "player": {
          "primary": "ff5500",
          "number": "ffffff",
          "border": "ff5500"
        },
        "goalkeeper": {
          "primary": "00cc33",
          "number": "ffffff",
          "border": "00cc33"
        }
      }
    },
    "coach": {
      "id": 636,
      "name": "R. Edwards",
      "photo": "https://media.api-sports.io/football/coachs/636.png"
    },
    "formation": "3-4-2-1",
    "startXI": [
      {
        "player": {
          "id": 8471,
          "name": "T. Kaminski",
          "number": 24,
          "pos": "G",
          "grid": "1:1"
        }
      },
      {
        "player": {
          "id": 153429,
          "name": "T. Mengi",
          "number": 15,
          "pos": "D",
          "grid": "2:3"
        }
      },
      {
        "player": {
          "id": 20203,
          "name": "T. Lockyer",
          "number": 4,
          "pos": "D",
          "grid": "2:2"
        }
      },
      {
        "player": {
          "id": 20206,
          "name": "G. Osho",
          "number": 2,
          "pos": "D",
          "grid": "2:1"
        }
      },
      {
        "player": {
          "id": 19829,
          "name": "A. Doughty",
          "number": 45,
          "pos": "M",
          "grid": "3:4"
        }
      },
      {
        "player": {
          "id": 19767,
          "name": "P. Mpanzu",
          "number": 17,
          "pos": "M",
          "grid": "3:3"
        }
      },
      {
        "player": {
          "id": 2287,
          "name": "R. Barkley",
          "number": 6,
          "pos": "M",
          "grid": "3:2"
        }
      },
      {
        "player": {
          "id": 19466,
          "name": "A. Bell",
          "number": 29,
          "pos": "M",
          "grid": "3:1"
        }
      },
      {
        "player": {
          "id": 18854,
          "name": "A. Townsend",
          "number": 30,
          "pos": "F",
          "grid": "4:2"
        }
      },
      {
        "player": {
          "id": 19365,
          "name": "C. Ogbene",
          "number": 7,
          "pos": "F",
          "grid": "4:1"
        }
      },
      {
        "player": {
          "id": 19083,
          "name": "C. Morris",
          "number": 9,
          "pos": "F",
          "grid": "5:1"
        }
      }
    ],
    "substitutes": [
      {
        "player": {
          "id": 906,
          "name": "T. Chong",
          "number": 14,
          "pos": "M",
          "grid": null
        }
      },
      {
        "player": {
          "id": 20189,
          "name": "J. Clark",
          "number": 18,
          "pos": "M",
          "grid": null
        }
      },
      {
        "player": {
          "id": 17641,
          "name": "E. Adebayo",
          "number": 11,
          "pos": "F",
          "grid": null
        }
      },
      {
        "player": {
          "id": 19802,
          "name": "J. Brown",
          "number": 19,
          "pos": "F",
          "grid": null
        }
      },
      {
        "player": {
          "id": 19759,
          "name": "L. Berry",
          "number": 8,
          "pos": "M",
          "grid": null
        }
      },
      {
        "player": {
          "id": 19061,
          "name": "T. Krul",
          "number": 23,
          "pos": "G",
          "grid": null
        }
      },
      {
        "player": {
          "id": 18747,
          "name": "R. Giles",
          "number": 26,
          "pos": "M",
          "grid": null
        }
      },
      {
        "player": {
          "id": 403065,
          "name": "J. Luker",
          "number": 47,
          "pos": "M",
          "grid": null
        }
      },
      {
        "player": {
          "id": 379627,
          "name": "Z. Nelson",
          "number": 43,
          "pos": "M",
          "grid": null
        }
      }
    ]
  },
  {
    "team": {
      "id": 52,
      "name": "Crystal Palace",
      "logo": "https://media.api-sports.io/football/teams/52.png",
      "colors": {
        "player": {
          "primary": "f8f7f7",
          "number": "ffffff",
          "border": "f8f7f7"
        },
        "goalkeeper": {
          "primary": "006600",
          "number": "ffffff",
          "border": "006600"
        }
      }
    },
    "coach": {
      "id": 9,
      "name": "R. Hodgson",
      "photo": "https://media.api-sports.io/football/coachs/9.png"
    },
    "formation": "4-2-3-1",
    "startXI": [
      {
        "player": {
          "id": 19143,
          "name": "S. Johnstone",
          "number": 1,
          "pos": "G",
          "grid": "1:1"
        }
      },
      {
        "player": {
          "id": 18847,
          "name": "J. Ward",
          "number": 2,
          "pos": "D",
          "grid": "2:4"
        }
      },
      {
        "player": {
          "id": 2729,
          "name": "J. Andersen",
          "number": 16,
          "pos": "D",
          "grid": "2:3"
        }
      },
      {
        "player": {
          "id": 67971,
          "name": "M. Guéhi",
          "number": 6,
          "pos": "D",
          "grid": "2:2"
        }
      },
      {
        "player": {
          "id": 182201,
          "name": "T. Mitchell",
          "number": 3,
          "pos": "D",
          "grid": "2:1"
        }
      },
      {
        "player": {
          "id": 3339,
          "name": "C. Doucouré",
          "number": 28,
          "pos": "M",
          "grid": "3:2"
        }
      },
      {
        "player": {
          "id": 2490,
          "name": "J. Lerma",
          "number": 8,
          "pos": "M",
          "grid": "3:1"
        }
      },
      {
        "player": {
          "id": 19617,
          "name": "M. Olise",
          "number": 7,
          "pos": "M",
          "grid": "4:3"
        }
      },
      {
        "player": {
          "id": 19586,
          "name": "E. Eze",
          "number": 10,
          "pos": "M",
          "grid": "4:2"
        }
      },
      {
        "player": {
          "id": 18843,
          "name": "J. Schlupp",
          "number": 15,
          "pos": "M",
          "grid": "4:1"
        }
      },
      {
        "player": {
          "id": 1135,
          "name": "O. Édouard",
          "number": 22,
          "pos": "F",
          "grid": "5:1"
        }
      }
    ],
    "substitutes": [
      {
        "player": {
          "id": 3428,
          "name": "J. Ayew",
          "number": 9,
          "pos": "F",
          "grid": null
        }
      },
      {
        "player": {
          "id": 18806,
          "name": "W. Hughes",
          "number": 19,
          "pos": "M",
          "grid": null
        }
      },
      {
        "player": {
          "id": 25927,
          "name": "J. Mateta",
          "number": 14,
          "pos": "F",
          "grid": null
        }
      },
      {
        "player": {
          "id": 152418,
          "name": "N. Ahamada",
          "number": 29,
          "pos": "M",
          "grid": null
        }
      },
      {
        "player": {
          "id": 311157,
          "name": "Matheus França",
          "number": 11,
          "pos": "F",
          "grid": null
        }
      },
      {
        "player": {
          "id": 126949,
          "name": "C. Richards",
          "number": 26,
          "pos": "D",
          "grid": null
        }
      },
      {
        "player": {
          "id": 1440,
          "name": "R. Holding",
          "number": 4,
          "pos": "D",
          "grid": null
        }
      },
      {
        "player": {
          "id": 19684,
          "name": "R. Matthews",
          "number": 31,
          "pos": "G",
          "grid": null
        }
      },
      {
        "player": {
          "id": 18862,
          "name": "N. Clyne",
          "number": 17,
          "pos": "D",
          "grid": null
        }
      }
    ]
  }
]